inkydev/__init__.py
inkydev-0.0.2.dist-info/LICENSE.txt
inkydev-0.0.2.dist-info/METADATA
inkydev-0.0.2.dist-info/WHEEL
inkydev-0.0.2.dist-info/top_level.txt
inkydev-0.0.2.dist-info/RECORD
